odoo9_addon_medical_patient_disease-9.0.1.0.0.99.dev5-py2.7-nspkg.pth
odoo9_addon_medical_patient_disease-9.0.1.0.0.99.dev5.dist-info/DESCRIPTION.rst
odoo9_addon_medical_patient_disease-9.0.1.0.0.99.dev5.dist-info/METADATA
odoo9_addon_medical_patient_disease-9.0.1.0.0.99.dev5.dist-info/RECORD
odoo9_addon_medical_patient_disease-9.0.1.0.0.99.dev5.dist-info/WHEEL
odoo9_addon_medical_patient_disease-9.0.1.0.0.99.dev5.dist-info/metadata.json
odoo9_addon_medical_patient_disease-9.0.1.0.0.99.dev5.dist-info/namespace_packages.txt
odoo9_addon_medical_patient_disease-9.0.1.0.0.99.dev5.dist-info/top_level.txt
odoo_addons/medical_patient_disease/README.rst
odoo_addons/medical_patient_disease/__init__.py
odoo_addons/medical_patient_disease/__openerp__.py
odoo_addons/medical_patient_disease/demo/medical_pathology_category_demo.xml
odoo_addons/medical_patient_disease/demo/medical_patient_demo.xml
odoo_addons/medical_patient_disease/demo/medical_patient_disease_demo.xml
odoo_addons/medical_patient_disease/i18n/es_CO.po
odoo_addons/medical_patient_disease/i18n/pt_BR.po
odoo_addons/medical_patient_disease/models/__init__.py
odoo_addons/medical_patient_disease/models/medical_patient.py
odoo_addons/medical_patient_disease/models/medical_patient_disease.py
odoo_addons/medical_patient_disease/security/ir.model.access.csv
odoo_addons/medical_patient_disease/static/description/icon.png
odoo_addons/medical_patient_disease/tests/__init__.py
odoo_addons/medical_patient_disease/tests/test_medical_patient.py
odoo_addons/medical_patient_disease/tests/test_medical_patient_disease.py
odoo_addons/medical_patient_disease/views/medical_menu.xml
odoo_addons/medical_patient_disease/views/medical_patient_disease_view.xml
odoo_addons/medical_patient_disease/views/medical_patient_view.xml
